arbiter/__about__.py
arbiter/__init__.py
arbiter/auth.py
arbiter/dict.py
arbiter/exceptions.py
arbiter/handlers.py
arbiter/registry.py
arbiter-1.1.2.dist-info/LICENSE
arbiter-1.1.2.dist-info/METADATA
arbiter-1.1.2.dist-info/WHEEL
arbiter-1.1.2.dist-info/top_level.txt
arbiter-1.1.2.dist-info/RECORD
