Metadata-Version: 2.1
Name: arbiter
Version: 1.1.2
Summary: Lightweight Data Handling Library
Home-page: https://github.com/rastern/arbiter
Author: R.A. Stern
Author-email: oss@rastern.me
License: LGPL 3.0
Platform: UNKNOWN
Classifier: Intended Audience :: Developers
Classifier: License :: OSI Approved :: GNU Lesser General Public License v3 or later (LGPLv3+)
Classifier: Operating System :: OS Independent
Classifier: Programming Language :: Python
Classifier: Programming Language :: Python :: 3
Classifier: Programming Language :: Python :: 3 :: Only
Classifier: Programming Language :: Python :: 3.6
Classifier: Programming Language :: Python :: 3.7
Classifier: Programming Language :: Python :: 3.8
Classifier: Programming Language :: Python :: 3.9
Classifier: Topic :: Software Development
Classifier: Topic :: Software Development :: Libraries
Requires-Python: >=3.6
Requires-Dist: umsg (>=1.0.4)
